tactus_data/__init__.py
tactus_data/datasets/__init__.py
tactus_data/datasets/dataset.py
tactus_data/datasets/ut_interaction.py
tactus_data/utils/__init__.py
tactus_data/utils/data_augment.py
tactus_data/utils/retracker.py
tactus_data/utils/skeleton.py
tactus_data/utils/skeletonrollingwindow.py
tactus_data/utils/thread_videocapture.py
tactus_data/utils/visualisation.py
tactus_data/utils/yolov7.py
tactus_data/utils/yolov8.py
test/test_skeletonization.py
tactus_data-1.2.0.dist-info/METADATA
tactus_data-1.2.0.dist-info/WHEEL
tactus_data-1.2.0.dist-info/top_level.txt
tactus_data-1.2.0.dist-info/RECORD
