Metadata-Version: 2.1
Name: tactus-data
Version: 1.2.0
Summary: Threatening activities classification toward users' security
Project-URL: repository, https://github.com/Cranfield-GDP3/TACTUS-data
Classifier: Development Status :: 5 - Production/Stable
Classifier: Intended Audience :: Developers
Classifier: Programming Language :: Python
Requires-Python: >=3.8
Requires-Dist: opencv-python
Requires-Dist: requests
Requires-Dist: tactus-deep-sort-realtime
Requires-Dist: torch
Requires-Dist: ultralytics
Requires-Dist: matplotlib
Requires-Dist: Pillow
Requires-Dist: numpy
Requires-Dist: tqdm
Requires-Dist: pytest
